{
  "project_info": {
    "project_number": "524602513703",
    "project_id": "ud-truck-sunter",
    "storage_bucket": "ud-truck-sunter.appspot.com"
  },
  "client": [
    {
      "client_info": {
        "mobilesdk_app_id": "1:524602513703:android:6a82091e4a2a2a2bb77102",
        "android_client_info": {
          "package_name": "com.daffa.ud_truck_booking"
        }
      },
      "oauth_client": [
        {
          "client_id": "524602513703-vvsgitmh47g0chj2ejc4b02relhjofeh.apps.googleusercontent.com",
          "client_type": 3
        }
      ],
      "api_key": [
        {
          "current_key": "AIzaSyAFq6yXsXxdrtYV1tnFMYtxLshLFaHQ_ZI"
        }
      ],
      "services": {
        "appinvite_service": {
          "other_platform_oauth_client": [
            {
              "client_id": "524602513703-vvsgitmh47g0chj2ejc4b02relhjofeh.apps.googleusercontent.com",
              "client_type": 3
            }
          ]
        }
      }
    }
  ],
  "configuration_version": "1"
}